diggity-0.1.1.dist-info/METADATA
diggity-0.1.1.dist-info/WHEEL
diggity-0.1.1.dist-info/licenses/LICENSE
diggity/__init__.py
diggity/diggity.cpython-313-aarch64-linux-gnu.so
diggity-0.1.1.dist-info/RECORD
