Metadata-Version: 2.4
Name: diggity
Version: 0.1.1
Classifier: Programming Language :: Rust
Classifier: Programming Language :: Python :: Implementation :: CPython
License-File: LICENSE
Summary: A utility library for working with nested objects and handling optional values. Inspired by Ruby `dig` function for safely accessing deeply nested structures
Author-email: Andrey Torsunov <andrey.torsunov@gmail.com>
Requires-Python: >=3.8
Project-URL: Homepage, https://github.com/gtors/diggity
Project-URL: Source, https://github.com/gtors/diggity
